forefront/__init__.py
forefront/forefront_client.py
forefront/chat/__init__.py
forefront/chat/chat.py
forefront/datasets/__init__.py
forefront/datasets/dataset.py
forefront/eval_sets/__init__.py
forefront/eval_sets/eval_set.py
forefront/fine_tunes/__init__.py
forefront/fine_tunes/fine_tunes.py
forefront/models/__init__.py
forefront/models/models.py
forefront/pipelines/__init__.py
forefront/pipelines/pipeline.py
forefront/threads/__init__.py
forefront/threads/threads.py
forefront/utils/__init__.py
forefront/utils/chat_utils.py
forefront/utils/text_utils.py
forefront/workflows/__init__.py
forefront/workflows/utils.py
forefront/workflows/workflow.py
forefront-0.3.53.dist-info/METADATA
forefront-0.3.53.dist-info/WHEEL
forefront-0.3.53.dist-info/top_level.txt
forefront-0.3.53.dist-info/RECORD
