Metadata-Version: 2.1
Name: forefront
Version: 0.3.53
Summary: UNKNOWN
Home-page: UNKNOWN
License: UNKNOWN
Platform: UNKNOWN
Requires-Dist: requests
Requires-Dist: aiohttp
Requires-Dist: asyncio
